odoo/addons/sale_fully_invoiced/README.rst
odoo/addons/sale_fully_invoiced/__init__.py
odoo/addons/sale_fully_invoiced/__manifest__.py
odoo/addons/sale_fully_invoiced/i18n/sale_fully_invoiced.pot
odoo/addons/sale_fully_invoiced/models/__init__.py
odoo/addons/sale_fully_invoiced/models/sale.py
odoo/addons/sale_fully_invoiced/readme/CONTRIBUTORS.rst
odoo/addons/sale_fully_invoiced/readme/DESCRIPTION.rst
odoo/addons/sale_fully_invoiced/readme/USAGE.rst
odoo/addons/sale_fully_invoiced/static/description/icon.png
odoo/addons/sale_fully_invoiced/static/description/index.html
odoo/addons/sale_fully_invoiced/tests/__init__.py
odoo/addons/sale_fully_invoiced/tests/test_sale_fully_invoiced.py
odoo/addons/sale_fully_invoiced/views/sale_views.xml
odoo_addon_sale_fully_invoiced-16.0.1.0.0.3.dist-info/METADATA
odoo_addon_sale_fully_invoiced-16.0.1.0.0.3.dist-info/WHEEL
odoo_addon_sale_fully_invoiced-16.0.1.0.0.3.dist-info/top_level.txt
odoo_addon_sale_fully_invoiced-16.0.1.0.0.3.dist-info/RECORD
